apprise/Apprise.py
apprise/Apprise.pyi
apprise/AppriseAsset.py
apprise/AppriseAsset.pyi
apprise/AppriseAttachment.py
apprise/AppriseAttachment.pyi
apprise/AppriseConfig.py
apprise/AppriseConfig.pyi
apprise/AppriseLocale.py
apprise/URLBase.py
apprise/URLBase.pyi
apprise/__init__.py
apprise/cli.py
apprise/common.py
apprise/common.pyi
apprise/logger.py
apprise/py.typed
apprise/utils.py
apprise/assets/NotifyXML-1.0.xsd
apprise/assets/themes/default/apprise-failure-128x128.ico
apprise/assets/themes/default/apprise-failure-128x128.png
apprise/assets/themes/default/apprise-failure-256x256.png
apprise/assets/themes/default/apprise-failure-32x32.png
apprise/assets/themes/default/apprise-failure-72x72.png
apprise/assets/themes/default/apprise-info-128x128.ico
apprise/assets/themes/default/apprise-info-128x128.png
apprise/assets/themes/default/apprise-info-256x256.png
apprise/assets/themes/default/apprise-info-32x32.png
apprise/assets/themes/default/apprise-info-72x72.png
apprise/assets/themes/default/apprise-logo.png
apprise/assets/themes/default/apprise-success-128x128.ico
apprise/assets/themes/default/apprise-success-128x128.png
apprise/assets/themes/default/apprise-success-256x256.png
apprise/assets/themes/default/apprise-success-32x32.png
apprise/assets/themes/default/apprise-success-72x72.png
apprise/assets/themes/default/apprise-warning-128x128.ico
apprise/assets/themes/default/apprise-warning-128x128.png
apprise/assets/themes/default/apprise-warning-256x256.png
apprise/assets/themes/default/apprise-warning-32x32.png
apprise/assets/themes/default/apprise-warning-72x72.png
apprise/attachment/AttachBase.py
apprise/attachment/AttachBase.pyi
apprise/attachment/AttachFile.py
apprise/attachment/AttachHTTP.py
apprise/attachment/__init__.py
apprise/config/ConfigBase.py
apprise/config/ConfigBase.pyi
apprise/config/ConfigFile.py
apprise/config/ConfigHTTP.py
apprise/config/ConfigMemory.py
apprise/config/__init__.py
apprise/i18n/__init__.py
apprise/plugins/NotifyBase.py
mka142_apprise-0.9.4.dist-info/LICENSE
mka142_apprise-0.9.4.dist-info/METADATA
mka142_apprise-0.9.4.dist-info/WHEEL
mka142_apprise-0.9.4.dist-info/entry_points.txt
mka142_apprise-0.9.4.dist-info/top_level.txt
mka142_apprise-0.9.4.dist-info/RECORD
