Metadata-Version: 2.1
Name: mka142-apprise
Version: 0.9.4
Summary: Push Notifications that work with just about every platform! | for nextcloud 21
Home-page: https://github.com/caronc/apprise
Author: Chris Caron
Author-email: lead2gold@gmail.com
License: MIT
Keywords: Push Notifications Alerts Email AWS SNS Boxcar ClickSend Dingtalk Discord Dbus Emby Faast FCM Flock Gitter Gnome Google Chat Gotify Growl Home Assistant IFTTT Join Kavenegar KODI Kumulos LaMetric MacOS Mailgun Matrix Mattermost MessageBird MSG91 Nexmo Nextcloud Notica Notifico Office365 OneSignal Opsgenie ParsePlatform PopcornNotify Prowl PushBullet Pushjet Pushed Pushover PushSafer Reddit Rocket.Chat Ryver SendGrid SimplePush Sinch Slack SMTP2Go SparkPost Spontit Stride Syslog Techulu
Platform: UNKNOWN
Classifier: Development Status :: 5 - Production/Stable
Classifier: Intended Audience :: Developers
Classifier: Intended Audience :: System Administrators
Classifier: Operating System :: OS Independent
Classifier: Natural Language :: English
Classifier: Programming Language :: Python
Classifier: Programming Language :: Python :: 2.7
Classifier: Programming Language :: Python :: 3
Classifier: License :: OSI Approved :: MIT License
Classifier: Topic :: Software Development :: Libraries :: Python Modules
Classifier: Topic :: Software Development :: Libraries :: Application Frameworks
Requires-Python: >=2.7
Requires-Dist: PyYAML
Requires-Dist: click (>=5.0)
Requires-Dist: cryptography
Requires-Dist: markdown
Requires-Dist: requests
Requires-Dist: requests-oauthlib
Requires-Dist: six
